leaderbird/__init__.py
leaderbird/__main__.py
leaderbird/app.py
leaderbird/config.py
leaderbird/elo.py
leaderbird/models.py
leaderbird-2.dist-info/licenses/LICENSE
leaderbird-2.dist-info/METADATA
leaderbird-2.dist-info/WHEEL
leaderbird-2.dist-info/top_level.txt
leaderbird-2.dist-info/RECORD
