Metadata-Version: 2.4
Name: leaderbird
Version: 2
Summary: A minimal starting package for leaderbird, for leaderboards and rankings.
Author-email: Robert James Toth <robert.toth@thetatech.ai>
License-File: LICENSE
Requires-Dist: flask>=2.3.0
Requires-Dist: python-dotenv>=0.19.0
Dynamic: license-file
